huaweicloudsdkclouddc/__init__.py
huaweicloudsdkclouddc/v1/__init__.py
huaweicloudsdkclouddc/v1/clouddc_async_client.py
huaweicloudsdkclouddc/v1/clouddc_client.py
huaweicloudsdkclouddc/v1/model/__init__.py
huaweicloudsdkclouddc/v1/model/alarm_daily_trend.py
huaweicloudsdkclouddc/v1/model/alarm_device_info.py
huaweicloudsdkclouddc/v1/model/alarm_group.py
huaweicloudsdkclouddc/v1/model/alarm_history.py
huaweicloudsdkclouddc/v1/model/alarm_host.py
huaweicloudsdkclouddc/v1/model/alarm_info.py
huaweicloudsdkclouddc/v1/model/alarm_level_info.py
huaweicloudsdkclouddc/v1/model/batch_create_irack_tags_request.py
huaweicloudsdkclouddc/v1/model/batch_create_irack_tags_response.py
huaweicloudsdkclouddc/v1/model/batch_create_tags_request.py
huaweicloudsdkclouddc/v1/model/batch_create_tags_response.py
huaweicloudsdkclouddc/v1/model/batch_delete_irack_tags_request.py
huaweicloudsdkclouddc/v1/model/batch_delete_irack_tags_response.py
huaweicloudsdkclouddc/v1/model/batch_delete_options.py
huaweicloudsdkclouddc/v1/model/batch_delete_tags_request.py
huaweicloudsdkclouddc/v1/model/batch_delete_tags_response.py
huaweicloudsdkclouddc/v1/model/capacity_bytes.py
huaweicloudsdkclouddc/v1/model/change_instance_password_options.py
huaweicloudsdkclouddc/v1/model/change_instance_password_request.py
huaweicloudsdkclouddc/v1/model/change_instance_password_response.py
huaweicloudsdkclouddc/v1/model/change_server_power_state_request.py
huaweicloudsdkclouddc/v1/model/change_server_power_state_response.py
huaweicloudsdkclouddc/v1/model/create_instance_opitons.py
huaweicloudsdkclouddc/v1/model/create_instance_opitons_placement.py
huaweicloudsdkclouddc/v1/model/create_instance_request.py
huaweicloudsdkclouddc/v1/model/create_instance_response.py
huaweicloudsdkclouddc/v1/model/delete_instance_request.py
huaweicloudsdkclouddc/v1/model/delete_instance_response.py
huaweicloudsdkclouddc/v1/model/delete_instances_request.py
huaweicloudsdkclouddc/v1/model/delete_instances_response.py
huaweicloudsdkclouddc-3.1.184.dist-info/METADATA
huaweicloudsdkclouddc-3.1.184.dist-info/WHEEL
huaweicloudsdkclouddc-3.1.184.dist-info/licenses/LICENSE
huaweicloudsdkclouddc-3.1.184.dist-info/RECORD
